{
  "id": "anthropology--anthropology-of-religion--t-mana-and-supernatural-power",
  "version": 1,
  "subject": "Anthropology",
  "subcategory": "Anthropology of Religion",
  "course_id": "anthropology--anthropology-of-religion",
  "chapter_id": "anthropology--anthropology-of-religion--ch01-what-is-religion",
  "title": "Mana and Supernatural Power",
  "emoji": "🕯️",
  "color": "#D97706",
  "description": "A quick win: understand Mana and Supernatural Power.",
  "is_free": false,
  "published": true,
  "story": {
    "hook": {
      "text": "A chief's cloak radiates power. A warrior's spear never misses. In Polynesia, that invisible force is called mana.",
      "visual": "⚡"
    },
    "buildup": {
      "text": "Mana is an impersonal supernatural force believed to reside in people, objects, or places across Melanesian cultures.",
      "visual": "🌺"
    },
    "discovery": {
      "text": "High-status people have more mana. Sacred objects carry it. Touching a chief's possessions can be dangerous.",
      "visual": "👑"
    },
    "twist": {
      "text": "Mana isn't unique to Polynesia. Similar concepts exist worldwide — qi in China, baraka in Islam, grace in Christianity.",
      "visual": "🌐"
    },
    "climax": {
      "text": "Mana shows that power isn't always political. In many cultures, supernatural energy underlies social authority.",
      "visual": "🔥"
    },
    "punchline": {
      "text": "Some power can't be seen, only felt.",
      "visual": "🌟"
    }
  },
  "quiz": {
    "question": "What is mana?",
    "options": [
      "A type of food in Polynesia",
      "An impersonal supernatural force in people and objects",
      "A form of currency"
    ],
    "correct": 1
  }
}
