{
  "id": "public-health--epidemiology-essentials--t-randomized-controlled-trials",
  "version": 1,
  "subject": "Public Health",
  "subcategory": "Epidemiology Essentials",
  "course_id": "public-health--epidemiology-essentials",
  "chapter_id": "public-health--epidemiology-essentials--ch03-study-designs",
  "title": "Randomized Controlled Trials",
  "emoji": "📊",
  "color": "#D97706",
  "description": "A quick, practical guide to Randomized Controlled Trials.",
  "is_free": false,
  "published": true,
  "story": {
    "hook": {
      "text": "The gold standard of evidence—randomly assign people to treatment or placebo and watch what happens.",
      "visual": "🏅"
    },
    "buildup": {
      "text": "RCTs eliminate confounding by randomly distributing all known and unknown factors between groups.",
      "visual": "🎲"
    },
    "discovery": {
      "text": "James Lind's 1747 trial of citrus fruit for scurvy is considered the first clinical trial in medical history.",
      "visual": "🍋"
    },
    "twist": {
      "text": "RCTs can't always be used—you can't randomly assign people to smoke or live in poverty for ethical reasons.",
      "visual": "⚖️"
    },
    "climax": {
      "text": "Despite limitations, RCTs remain the most reliable way to determine whether a treatment actually works.",
      "visual": "🔬"
    },
    "punchline": {
      "text": "Randomization is the closest science gets to a fair test.",
      "visual": "🎯"
    }
  },
  "quiz": {
    "question": "Why are RCTs considered the gold standard?",
    "options": [
      "Randomization eliminates confounding factors",
      "They are the cheapest to conduct",
      "They can study any exposure"
    ],
    "correct": 0
  }
}
