{
  "id": "science--electricity-and-magnetism--t-maxwell-s-equations-unifying-the-forces",
  "version": 1,
  "subject": "Science",
  "subcategory": "Electricity and Magnetism",
  "course_id": "science--electricity-and-magnetism",
  "chapter_id": "science--electricity-and-magnetism--ch04-electromagnetism",
  "title": "Maxwell's Equations: Unifying the Forces",
  "emoji": "⚡",
  "color": "#D97706",
  "description": "A tiny lesson with a big payoff: Maxwell's Equations: Unifying the Forces.",
  "is_free": false,
  "published": true,
  "story": {
    "hook": {
      "text": "James Clerk Maxwell wrote four equations that unified electricity, magnetism, and light.",
      "visual": "📐"
    },
    "buildup": {
      "text": "In the 1860s, Maxwell combined all known laws of electricity and magnetism into one framework.",
      "visual": "🧩"
    },
    "discovery": {
      "text": "His equations predicted electromagnetic waves that travel at the speed of light.",
      "visual": "🌊"
    },
    "twist": {
      "text": "Maxwell realized light itself is an electromagnetic wave — not a separate phenomenon.",
      "visual": "💡"
    },
    "climax": {
      "text": "His work laid the foundation for radio, TV, Wi-Fi, X-rays, and all wireless communication.",
      "visual": "📡"
    },
    "punchline": {
      "text": "Four equations explain light, radio, and X-rays. Maxwell unified forces with math.",
      "visual": "🧠"
    }
  },
  "quiz": {
    "question": "What did Maxwell's equations reveal about light?",
    "options": [
      "Light is an electromagnetic wave",
      "Light is made of particles only",
      "Light requires a medium to travel"
    ],
    "correct": 0
  }
}
