{
  "id": "sports--combat-sports-history--t-martial-arts-in-cinema",
  "version": 1,
  "subject": "Sports",
  "subcategory": "Combat Sports History",
  "course_id": "sports--combat-sports-history",
  "chapter_id": "sports--combat-sports-history--ch06-culture-and-impact",
  "title": "Martial Arts in Cinema",
  "emoji": "🥊",
  "color": "#B91C1C",
  "description": "A micro-lesson that makes Martial Arts in Cinema usable.",
  "is_free": false,
  "published": true,
  "story": {
    "hook": {
      "text": "Bruce Lee, Jackie Chan, and Jet Li made martial arts cinema a global genre worth billions.",
      "visual": "🎬"
    },
    "buildup": {
      "text": "Hong Kong's Shaw Brothers studio produced hundreds of kung fu films in the 1960s and 70s, creating a genre.",
      "visual": "🇭🇰"
    },
    "discovery": {
      "text": "Bruce Lee's 'Enter the Dragon' (1973) crossed over to Western audiences and made martial arts mainstream entertainment.",
      "visual": "🐉"
    },
    "twist": {
      "text": "Jackie Chan reinvented the genre by adding comedy and performing his own death-defying stunts with no doubles.",
      "visual": "😄"
    },
    "climax": {
      "text": "Films like 'Crouching Tiger, Hidden Dragon' and 'The Matrix' brought martial arts choreography to Hollywood's elite.",
      "visual": "🏆"
    },
    "punchline": {
      "text": "Hong Kong choreography shaped Hollywood action. Every fight scene has martial arts DNA.",
      "visual": "🎥"
    }
  },
  "quiz": {
    "question": "Which film brought martial arts to mainstream Western audiences?",
    "options": [
      "Bruce Lee's Enter the Dragon in 1973",
      "Jackie Chan's Rush Hour in 1998",
      "The Matrix in 1999"
    ],
    "correct": 0
  }
}
