{
  "id": "ux-research--accessibility-champions--t-error-prevention-and-recovery",
  "version": 1,
  "subject": "UX & Research",
  "subcategory": "Accessibility Champions",
  "course_id": "ux-research--accessibility-champions",
  "chapter_id": "ux-research--accessibility-champions--ch04-cognitive-accessibility",
  "title": "Error Prevention and Recovery",
  "emoji": "♿",
  "color": "#14B8A6",
  "description": "A 1-minute de-risking session on Error Prevention and Recovery.",
  "is_free": false,
  "published": true,
  "story": {
    "hook": {
      "text": "A user deletes an email. No undo, no confirmation. Gone forever. One wrong click, permanent loss.",
      "visual": "🗑️"
    },
    "buildup": {
      "text": "Users with attention or memory difficulties make more errors. Accessible design expects mistakes.",
      "visual": "🧠"
    },
    "discovery": {
      "text": "Inline validation catches errors as users type. Catching 'invalid email' early saves form frustration.",
      "visual": "✅"
    },
    "twist": {
      "text": "Confirmation dialogs aren't enough. Users click 'OK' reflexively. Undo is better — act first, recover after.",
      "visual": "↩️"
    },
    "climax": {
      "text": "Every destructive action needs an escape hatch. Design for recovery, not just prevention.",
      "visual": "🛡️"
    },
    "punchline": {
      "text": "Expect errors. Undo beats confirmation. Recovery builds confidence.",
      "visual": "🎯"
    }
  },
  "quiz": {
    "question": "Why is undo better than confirmation dialogs for error prevention?",
    "options": [
      "Users click 'OK' reflexively on confirmation dialogs, but undo lets them act first and recover after",
      "Undo buttons are cheaper to implement",
      "Confirmation dialogs slow down all users equally"
    ],
    "correct": 0
  }
}
