{
  "categoryId": "anthropology",
  "subject": "Anthropology",
  "courseId": "anthropology--anthropology-of-religion",
  "courseTitle": "Anthropology of Religion",
  "emoji": "🕯️",
  "color": "#D97706",
  "requireAuthoredStory": true,
  "chapters": [
    { "id": "anthropology--anthropology-of-religion--ch01-what-is-religion", "title": "What Is Religion?", "position": 1 },
    { "id": "anthropology--anthropology-of-religion--ch02-myth-and-cosmology", "title": "Myth and Cosmology", "position": 2 },
    { "id": "anthropology--anthropology-of-religion--ch03-ritual-and-practice", "title": "Ritual and Practice", "position": 3 },
    { "id": "anthropology--anthropology-of-religion--ch04-specialists-and-authority", "title": "Specialists and Authority", "position": 4 },
    { "id": "anthropology--anthropology-of-religion--ch05-religion-and-society", "title": "Religion and Society", "position": 5 },
    { "id": "anthropology--anthropology-of-religion--ch06-religion-in-modern-world", "title": "Religion in the Modern World", "position": 6 }
  ],
  "topics": [
    {
      "chapter_id": "anthropology--anthropology-of-religion--ch01-what-is-religion",
      "title": "Defining Religion",
      "is_free": true,
      "story": {
        "hook": { "text": "Is Buddhism a religion? It has no creator god. Is football? It has rituals, devotion, and sacred spaces.", "visual": "🤔" },
        "buildup": { "text": "Anthropologists struggle to define religion because it takes radically different forms across cultures.", "visual": "🌍" },
        "discovery": { "text": "Clifford Geertz defined it as a system of symbols that creates powerful moods and motivations in people.", "visual": "📖" },
        "twist": { "text": "Any definition that fits all religions either becomes too broad (including football) or too narrow (excluding Buddhism).", "visual": "⚖️" },
        "climax": { "text": "Religion may resist a single definition. Anthropology studies it not by defining it but by observing what it does.", "visual": "🔍" },
        "punchline": { "text": "Religion is easier to recognize than to define.", "visual": "👁️" }
      },
      "quiz": {
        "question": "Why is religion hard to define anthropologically?",
        "options": ["All religions are identical", "It takes radically different forms across cultures", "Only Western religions count"],
        "correct": 1
      }
    },
    {
      "chapter_id": "anthropology--anthropology-of-religion--ch01-what-is-religion",
      "title": "Animism",
      "is_free": false,
      "story": {
        "hook": { "text": "The river has a spirit. The mountain has a will. The tree remembers. For animists, nature is alive and aware.", "visual": "🌳" },
        "buildup": { "text": "Animism is the belief that non-human entities — animals, plants, rivers, and stones — possess spirits or souls.", "visual": "🌊" },
        "discovery": { "text": "Edward Tylor called it the earliest form of religion. He saw it as primitive, but that view is now rejected.", "visual": "📚" },
        "twist": { "text": "Modern anthropologists see animism not as a stage but as a relational worldview — being in nature, not above it.", "visual": "🌿" },
        "climax": { "text": "Animism challenges Western assumptions. It offers a view where humans aren't masters of nature but participants in it.", "visual": "🤝" },
        "punchline": { "text": "In animism, nature is a community of persons.", "visual": "🌍" }
      },
      "quiz": {
        "question": "What is animism?",
        "options": ["Worship of a single god", "The belief that non-human entities possess spirits", "A modern New Age movement"],
        "correct": 1
      }
    },
    {
      "chapter_id": "anthropology--anthropology-of-religion--ch01-what-is-religion",
      "title": "The Sacred and Profane",
      "is_free": false,
      "story": {
        "hook": { "text": "A piece of bread is just food. But in a church, that same bread becomes the body of God. What changed?", "visual": "🍞" },
        "buildup": { "text": "Durkheim divided the world into sacred (set apart, forbidden) and profane (ordinary, everyday) realms.", "visual": "⚖️" },
        "discovery": { "text": "Religion, for Durkheim, is a unified system of beliefs and practices relative to sacred things.", "visual": "📖" },
        "twist": { "text": "The sacred isn't inherently special. Society makes things sacred by investing them with collective emotion and meaning.", "visual": "🏛️" },
        "climax": { "text": "Durkheim argued that when people worship the sacred, they're actually worshipping society itself in symbolic form.", "visual": "👥" },
        "punchline": { "text": "The sacred is society in disguise.", "visual": "🎭" }
      },
      "quiz": {
        "question": "What did Durkheim mean by the sacred?",
        "options": ["Things that are naturally holy", "Things set apart by society and invested with collective meaning", "Only objects in churches"],
        "correct": 1
      }
    },
    {
      "chapter_id": "anthropology--anthropology-of-religion--ch01-what-is-religion",
      "title": "Mana and Supernatural Power",
      "is_free": false,
      "story": {
        "hook": { "text": "A chief's cloak radiates power. A warrior's spear never misses. In Polynesia, that invisible force is called mana.", "visual": "⚡" },
        "buildup": { "text": "Mana is an impersonal supernatural force believed to reside in people, objects, or places across Melanesian cultures.", "visual": "🌺" },
        "discovery": { "text": "High-status people have more mana. Sacred objects carry it. Touching a chief's possessions can be dangerous.", "visual": "👑" },
        "twist": { "text": "Mana isn't unique to Polynesia. Similar concepts exist worldwide — qi in China, baraka in Islam, grace in Christianity.", "visual": "🌐" },
        "climax": { "text": "Mana shows that power isn't always political. In many cultures, supernatural energy underlies social authority.", "visual": "🔥" },
        "punchline": { "text": "Some power can't be seen, only felt.", "visual": "🌟" }
      },
      "quiz": {
        "question": "What is mana?",
        "options": ["A type of food in Polynesia", "An impersonal supernatural force in people and objects", "A form of currency"],
        "correct": 1
      }
    },
    {
      "chapter_id": "anthropology--anthropology-of-religion--ch01-what-is-religion",
      "title": "Religion vs. Magic",
      "is_free": false,
      "story": {
        "hook": { "text": "A priest prays to God for rain. A sorcerer performs a spell to make it rain. What's the difference?", "visual": "🌧️" },
        "buildup": { "text": "Frazer distinguished magic (manipulating supernatural forces) from religion (submitting to higher powers).", "visual": "📖" },
        "discovery": { "text": "Malinowski saw magic as practical and goal-oriented, while religion addressed existential anxieties and social bonds.", "visual": "🎯" },
        "twist": { "text": "The boundary is blurry. Prayer can feel like a spell. Rituals blend magic and religion in most living traditions.", "visual": "🔀" },
        "climax": { "text": "The magic-religion divide is a Western construct. Most cultures don't separate them so neatly.", "visual": "🌍" },
        "punchline": { "text": "Magic and religion share the same roots.", "visual": "🌳" }
      },
      "quiz": {
        "question": "How did Frazer distinguish magic from religion?",
        "options": ["Magic is real and religion is not", "Magic manipulates forces; religion submits to higher powers", "There is no difference at all"],
        "correct": 1
      }
    },
    {
      "chapter_id": "anthropology--anthropology-of-religion--ch02-myth-and-cosmology",
      "title": "What Is Myth?",
      "is_free": true,
      "story": {
        "hook": { "text": "Myth isn't a lie. For the people who tell it, myth is the deepest truth — the story of how everything began.", "visual": "📜" },
        "buildup": { "text": "Myths are sacred narratives that explain origins, natural phenomena, and the moral order of a society.", "visual": "🌅" },
        "discovery": { "text": "They justify institutions, explain suffering, and give meaning to rituals. Myth is a culture's operating manual.", "visual": "📖" },
        "twist": { "text": "Calling something a myth usually means dismissing it. But anthropologists take myths seriously as cultural documents.", "visual": "🔍" },
        "climax": { "text": "Myths aren't primitive science. They're symbolic systems that organize a community's deepest values and fears.", "visual": "🧠" },
        "punchline": { "text": "Myths are truths dressed as stories.", "visual": "📚" }
      },
      "quiz": {
        "question": "How do anthropologists view myths?",
        "options": ["As false stories that need debunking", "As sacred narratives revealing cultural values and meaning", "As entertainment with no deeper significance"],
        "correct": 1
      }
    },
    {
      "chapter_id": "anthropology--anthropology-of-religion--ch02-myth-and-cosmology",
      "title": "Creation Myths",
      "is_free": false,
      "story": {
        "hook": { "text": "In Genesis, God speaks the world into being. In Hindu myth, Brahma dreams it. Every culture starts with a story.", "visual": "🌍" },
        "buildup": { "text": "Creation myths explain how the world, humans, and social order came to exist — the ultimate origin story.", "visual": "🌅" },
        "discovery": { "text": "Common motifs include emergence from water, a cosmic egg, sacrifice of a primordial being, or a divine word.", "visual": "🥚" },
        "twist": { "text": "Creation myths don't just explain nature. They justify the current social order — who rules, who serves, and why.", "visual": "👑" },
        "climax": { "text": "Every creation myth encodes a worldview. How you begin the story shapes how you understand your place in it.", "visual": "🗺️" },
        "punchline": { "text": "The beginning story defines everything after.", "visual": "📖" }
      },
      "quiz": {
        "question": "What social function do creation myths serve?",
        "options": ["They are only about nature", "They justify the existing social order and values", "They have no deeper meaning"],
        "correct": 1
      }
    },
    {
      "chapter_id": "anthropology--anthropology-of-religion--ch02-myth-and-cosmology",
      "title": "Trickster Figures",
      "is_free": false,
      "story": {
        "hook": { "text": "Coyote steals fire. Anansi outwits the gods. Loki breaks every rule. Tricksters appear in myths across the globe.", "visual": "🦊" },
        "buildup": { "text": "Trickster figures are mythological characters who break rules, cross boundaries, and disrupt the established order.", "visual": "🃏" },
        "discovery": { "text": "They're often creators and destroyers at once — bringing fire, death, or language through cunning, not force.", "visual": "🔥" },
        "twist": { "text": "Tricksters teach by bad example. Their chaos reveals why rules exist — and sometimes exposes their absurdity.", "visual": "😏" },
        "climax": { "text": "Tricksters embody ambiguity. In a world of fixed categories, they remind us that boundaries can be crossed.", "visual": "🚪" },
        "punchline": { "text": "Every culture needs a rule-breaker in its stories.", "visual": "🎭" }
      },
      "quiz": {
        "question": "What role do trickster figures play in myths?",
        "options": ["They enforce all social rules", "They break rules and reveal boundaries through chaos", "They are always evil villains"],
        "correct": 1
      }
    },
    {
      "chapter_id": "anthropology--anthropology-of-religion--ch02-myth-and-cosmology",
      "title": "Structuralism and Myth",
      "is_free": false,
      "story": {
        "hook": { "text": "Raw vs. cooked. Nature vs. culture. Life vs. death. Lévi-Strauss saw myths as systems of oppositions.", "visual": "🔀" },
        "buildup": { "text": "Lévi-Strauss argued that myths resolve fundamental contradictions by organizing them into binary oppositions.", "visual": "📊" },
        "discovery": { "text": "Myths work like language — their meaning comes from relationships between elements, not from individual stories.", "visual": "🧩" },
        "twist": { "text": "Critics say structuralism forces myths into neat pairs. Real myths are messier and more ambiguous than binaries allow.", "visual": "🤔" },
        "climax": { "text": "Structuralism revealed deep patterns beneath surface stories. Even flawed, it changed how we read mythology.", "visual": "🔍" },
        "punchline": { "text": "Myths hide their logic in oppositions.", "visual": "⚖️" }
      },
      "quiz": {
        "question": "What did Lévi-Strauss argue about myths?",
        "options": ["Myths are random and meaningless", "Myths resolve contradictions through binary oppositions", "Myths are literal historical accounts"],
        "correct": 1
      }
    },
    {
      "chapter_id": "anthropology--anthropology-of-religion--ch02-myth-and-cosmology",
      "title": "Cosmology and Worldview",
      "is_free": false,
      "story": {
        "hook": { "text": "The Navajo walk in beauty between four sacred mountains. Their landscape is their cosmology made physical.", "visual": "🏔️" },
        "buildup": { "text": "Cosmology is a society's model of the universe — its structure, origins, and the place of humans within it.", "visual": "🌌" },
        "discovery": { "text": "Cosmologies shape daily life: when to plant, how to heal, where to bury the dead, and which direction to pray.", "visual": "🙏" },
        "twist": { "text": "Western cosmology separates nature and culture. Many Indigenous cosmologies see no such divide — all is interconnected.", "visual": "🌐" },
        "climax": { "text": "Cosmology isn't abstract philosophy. It's the invisible map that guides every action and decision in a culture.", "visual": "🗺️" },
        "punchline": { "text": "How you see the universe shapes how you live in it.", "visual": "🔭" }
      },
      "quiz": {
        "question": "What is cosmology in anthropology?",
        "options": ["The study of outer space", "A society's model of the universe and humanity's place in it", "A type of religious prayer"],
        "correct": 1
      }
    },
    {
      "chapter_id": "anthropology--anthropology-of-religion--ch03-ritual-and-practice",
      "title": "Sacrifice",
      "is_free": true,
      "story": {
        "hook": { "text": "The Aztecs offered human hearts to the sun. The Greeks burned cattle. Christians celebrate bread and wine as sacrifice.", "visual": "🔥" },
        "buildup": { "text": "Sacrifice is the ritual offering of something valuable — food, animals, or lives — to supernatural beings.", "visual": "⚱️" },
        "discovery": { "text": "It creates a reciprocal bond: humans give, and gods protect. Sacrifice is exchange between the natural and supernatural.", "visual": "🤝" },
        "twist": { "text": "Hubert and Mauss argued that sacrifice transforms the ordinary into the sacred through a ritual act of destruction.", "visual": "✨" },
        "climax": { "text": "Sacrifice appears in nearly every religion. It reveals humanity's deep need to communicate with invisible powers.", "visual": "🌟" },
        "punchline": { "text": "To give to the gods is to speak their language.", "visual": "🗣️" }
      },
      "quiz": {
        "question": "What is the purpose of sacrifice in religion?",
        "options": ["Pure destruction with no meaning", "Creating a reciprocal bond between humans and the supernatural", "Only an ancient practice with no logic"],
        "correct": 1
      }
    },
    {
      "chapter_id": "anthropology--anthropology-of-religion--ch03-ritual-and-practice",
      "title": "Pilgrimage",
      "is_free": false,
      "story": {
        "hook": { "text": "Millions walk to Mecca each year. Others trek to Varanasi or Lourdes. Sacred journeys cross every faith.", "visual": "🕌" },
        "buildup": { "text": "Pilgrimage is a religious journey to a sacred place, undertaken as an act of devotion, penance, or spiritual seeking.", "visual": "🚶" },
        "discovery": { "text": "Victor Turner described pilgrimage as a liminal experience — pilgrims leave ordinary life and enter sacred time.", "visual": "🚪" },
        "twist": { "text": "Pilgrimage creates communitas — a temporary bond of equality among strangers united by shared spiritual purpose.", "visual": "🤝" },
        "climax": { "text": "Pilgrimage transforms the individual. The journey itself, not just the destination, is where the sacred is found.", "visual": "🌟" },
        "punchline": { "text": "The path is the prayer.", "visual": "👣" }
      },
      "quiz": {
        "question": "What is communitas in pilgrimage?",
        "options": ["A type of temple", "A bond of equality among strangers sharing a spiritual journey", "A payment made at sacred sites"],
        "correct": 1
      }
    },
    {
      "chapter_id": "anthropology--anthropology-of-religion--ch03-ritual-and-practice",
      "title": "Prayer and Meditation",
      "is_free": false,
      "story": {
        "hook": { "text": "A Muslim bows five times daily. A Buddhist sits in silence. Both are reaching toward something beyond the visible.", "visual": "🧘" },
        "buildup": { "text": "Prayer addresses supernatural beings directly — asking, thanking, confessing, or praising through words or silence.", "visual": "🙏" },
        "discovery": { "text": "Meditation turns inward, seeking altered states, insight, or union with the divine through focused mental practice.", "visual": "🧠" },
        "twist": { "text": "Both practices reshape the practitioner. Neuroscience shows that prayer and meditation change brain activity measurably.", "visual": "📊" },
        "climax": { "text": "Whether outward or inward, these practices reveal a universal human impulse to connect with something greater.", "visual": "🌌" },
        "punchline": { "text": "Humans reach for the invisible daily.", "visual": "🌟" }
      },
      "quiz": {
        "question": "How do prayer and meditation differ?",
        "options": ["They are exactly the same", "Prayer addresses the supernatural; meditation turns inward", "Only prayer has any real effects"],
        "correct": 1
      }
    },
    {
      "chapter_id": "anthropology--anthropology-of-religion--ch03-ritual-and-practice",
      "title": "Divination",
      "is_free": false,
      "story": {
        "hook": { "text": "Read the cracks in a heated bone. Toss cowrie shells. Study bird flights. Every culture finds ways to see the future.", "visual": "🔮" },
        "buildup": { "text": "Divination is the practice of seeking hidden knowledge through supernatural means — omens, oracles, or sacred objects.", "visual": "🃏" },
        "discovery": { "text": "It helps people make decisions under uncertainty: when to plant, whom to marry, who caused an illness.", "visual": "🤔" },
        "twist": { "text": "Divination isn't random belief. It provides a culturally trusted framework for making choices in an unpredictable world.", "visual": "🧭" },
        "climax": { "text": "Divination turns chaos into meaning. It gives people agency by providing answers when ordinary knowledge falls short.", "visual": "💡" },
        "punchline": { "text": "When knowledge ends, divination begins.", "visual": "🌅" }
      },
      "quiz": {
        "question": "What is the social function of divination?",
        "options": ["Pure entertainment", "Providing culturally trusted frameworks for decisions under uncertainty", "Predicting the future with perfect accuracy"],
        "correct": 1
      }
    },
    {
      "chapter_id": "anthropology--anthropology-of-religion--ch03-ritual-and-practice",
      "title": "Ancestor Worship",
      "is_free": false,
      "story": {
        "hook": { "text": "In many cultures, the dead don't leave. They watch, judge, and protect. Ancestors are the original authority figures.", "visual": "👻" },
        "buildup": { "text": "Ancestor worship involves rituals honoring dead relatives who are believed to retain influence over the living.", "visual": "🕯️" },
        "discovery": { "text": "Offerings of food, drink, and prayers maintain the relationship. Neglecting ancestors can bring illness or misfortune.", "visual": "🍚" },
        "twist": { "text": "Ancestor worship reinforces family bonds across generations. The dead become moral enforcers of social norms.", "visual": "⚖️" },
        "climax": { "text": "Honoring the dead isn't just grief. It's a social system that links past, present, and future through sacred obligation.", "visual": "🔗" },
        "punchline": { "text": "The dead still shape the living.", "visual": "🌳" }
      },
      "quiz": {
        "question": "What social function does ancestor worship serve?",
        "options": ["Only mourning the dead", "Reinforcing family bonds and enforcing social norms across generations", "Preventing ghosts from appearing"],
        "correct": 1
      }
    },
    {
      "chapter_id": "anthropology--anthropology-of-religion--ch04-specialists-and-authority",
      "title": "Shamanism",
      "is_free": true,
      "story": {
        "hook": { "text": "The shaman drums, chants, and enters a trance. His soul leaves his body to negotiate with spirits on behalf of the sick.", "visual": "🥁" },
        "buildup": { "text": "Shamans are religious specialists who enter altered states to communicate with the spirit world for healing or guidance.", "visual": "🌀" },
        "discovery": { "text": "Found across Siberia, the Americas, and Southeast Asia, shamanism is one of the oldest forms of religious practice.", "visual": "🌍" },
        "twist": { "text": "Shamans aren't priests. They earn their role through crisis, visions, or illness — not institutional training.", "visual": "⚡" },
        "climax": { "text": "Shamanism reveals that religious authority can come from personal experience, not just inherited or institutional power.", "visual": "🔥" },
        "punchline": { "text": "The shaman's power comes from suffering, not from rank.", "visual": "💫" }
      },
      "quiz": {
        "question": "How do shamans differ from priests?",
        "options": ["Shamans are trained in institutions", "Shamans gain authority through personal spiritual experience", "There is no difference between them"],
        "correct": 1
      }
    },
    {
      "chapter_id": "anthropology--anthropology-of-religion--ch04-specialists-and-authority",
      "title": "Priests and Priesthoods",
      "is_free": false,
      "story": {
        "hook": { "text": "The priest recites ancient words in a sacred hall at a set time. His authority comes from the institution, not visions.", "visual": "⛪" },
        "buildup": { "text": "Priests are full-time religious specialists whose authority comes from their position within a religious institution.", "visual": "📜" },
        "discovery": { "text": "They perform standardized rituals, interpret sacred texts, and mediate between the community and the divine.", "visual": "📖" },
        "twist": { "text": "Priesthoods consolidate religious power. They control sacred knowledge and access to the divine, forming hierarchy.", "visual": "👑" },
        "climax": { "text": "Priests represent religion institutionalized. Where shamans are freelance, priests are part of a larger power structure.", "visual": "🏛️" },
        "punchline": { "text": "Institutional religion needs institutional specialists.", "visual": "⚙️" }
      },
      "quiz": {
        "question": "Where does a priest's authority come from?",
        "options": ["Personal visions and trances", "Their position within a religious institution", "Physical strength and wealth"],
        "correct": 1
      }
    },
    {
      "chapter_id": "anthropology--anthropology-of-religion--ch04-specialists-and-authority",
      "title": "Prophets and Charisma",
      "is_free": false,
      "story": {
        "hook": { "text": "Moses, Muhammad, and the Ghost Dance prophets all claimed divine messages. Prophets challenge the religious status quo.", "visual": "📢" },
        "buildup": { "text": "Prophets are individuals who claim direct divine revelation and use it to call for social or spiritual change.", "visual": "⚡" },
        "discovery": { "text": "Weber called their authority charismatic — based on personal magnetism and perceived divine connection, not tradition.", "visual": "🌟" },
        "twist": { "text": "Prophetic movements often arise during crisis. Social upheaval creates the conditions for new religious voices.", "visual": "🌊" },
        "climax": { "text": "Prophets disrupt existing religions. Their success creates new institutions — which eventually need their own prophets.", "visual": "🔄" },
        "punchline": { "text": "Every new religion started with a prophetic voice.", "visual": "🗣️" }
      },
      "quiz": {
        "question": "What is charismatic authority?",
        "options": ["Power based on wealth and land", "Authority from personal magnetism and perceived divine connection", "Inherited political power"],
        "correct": 1
      }
    },
    {
      "chapter_id": "anthropology--anthropology-of-religion--ch04-specialists-and-authority",
      "title": "Witchcraft Accusations",
      "is_free": false,
      "story": {
        "hook": { "text": "Your neighbor's cow dies after your argument. She accuses you of witchcraft. In many societies, this is serious.", "visual": "🐄" },
        "buildup": { "text": "Witchcraft accusations are social mechanisms that express tensions, jealousy, and conflict within communities.", "visual": "😠" },
        "discovery": { "text": "Evans-Pritchard showed that among the Azande, witchcraft accusations target people with whom you already have conflict.", "visual": "📖" },
        "twist": { "text": "Accusations reveal social fault lines. They often target the marginal, the envied, or those who disrupt social order.", "visual": "🎯" },
        "climax": { "text": "Witchcraft accusations are not about magic. They're about power, envy, and social control wearing a supernatural mask.", "visual": "🎭" },
        "punchline": { "text": "Accusations say more about the accuser than the accused.", "visual": "🪞" }
      },
      "quiz": {
        "question": "What do witchcraft accusations often reflect?",
        "options": ["Actual supernatural powers", "Social tensions, jealousy, and power conflicts", "Random accusations with no pattern"],
        "correct": 1
      }
    },
    {
      "chapter_id": "anthropology--anthropology-of-religion--ch04-specialists-and-authority",
      "title": "Spirit Possession",
      "is_free": false,
      "story": {
        "hook": { "text": "She shakes, speaks in a strange voice, and doesn't remember afterward. The community says a spirit entered her.", "visual": "🌀" },
        "buildup": { "text": "Spirit possession is the belief that a supernatural being can temporarily inhabit and control a human body.", "visual": "👤" },
        "discovery": { "text": "It occurs worldwide — from Haitian Vodou to Ethiopian zar cults to Pentecostal Christian speaking in tongues.", "visual": "🌍" },
        "twist": { "text": "I.M. Lewis argued that possession often empowers the powerless — women and marginal groups use it to gain voice.", "visual": "📢" },
        "climax": { "text": "Possession is not just belief. It's a social performance that gives the dispossessed a way to speak and be heard.", "visual": "🎤" },
        "punchline": { "text": "The voiceless find power through spirits.", "visual": "👻" }
      },
      "quiz": {
        "question": "How can spirit possession function socially?",
        "options": ["It only causes harm to communities", "It can empower marginalized people to gain a voice", "It has no social significance"],
        "correct": 1
      }
    },
    {
      "chapter_id": "anthropology--anthropology-of-religion--ch05-religion-and-society",
      "title": "Religion and Social Cohesion",
      "is_free": true,
      "story": {
        "hook": { "text": "When a village prays together, shares a meal, and sings the same hymn, something binds them beyond words.", "visual": "🤝" },
        "buildup": { "text": "Durkheim argued that religion's primary function is to unite individuals into a moral community through shared rituals.", "visual": "🏛️" },
        "discovery": { "text": "Collective rituals create solidarity. The shared emotional experience reinforces group identity and mutual obligation.", "visual": "🎶" },
        "twist": { "text": "Religion doesn't just unite — it also divides. It marks insiders from outsiders, believers from heretics.", "visual": "🚪" },
        "climax": { "text": "Religion is social glue and social wall. It binds communities together while drawing boundaries against others.", "visual": "🧱" },
        "punchline": { "text": "Shared belief builds shared belonging.", "visual": "🏠" }
      },
      "quiz": {
        "question": "What did Durkheim say about religion's social function?",
        "options": ["Religion only causes division", "It unites individuals into a moral community through shared rituals", "Religion has no social effects"],
        "correct": 1
      }
    },
    {
      "chapter_id": "anthropology--anthropology-of-religion--ch05-religion-and-society",
      "title": "Religion and Inequality",
      "is_free": false,
      "story": {
        "hook": { "text": "The king rules by divine right. The poor inherit heaven later. Religion often justifies who has power and who doesn't.", "visual": "👑" },
        "buildup": { "text": "Marx called religion the opium of the people — a tool that dulls pain and prevents rebellion against injustice.", "visual": "💊" },
        "discovery": { "text": "Religious hierarchies mirror social ones. Priests serve kings; gods sanction the social order as divinely ordained.", "visual": "⛪" },
        "twist": { "text": "But religion also fuels revolution. Liberation theology and abolitionism used faith to fight injustice, not support it.", "visual": "✊" },
        "climax": { "text": "Religion can legitimize power or challenge it. The same texts inspire obedience and rebellion, depending on who reads.", "visual": "📖" },
        "punchline": { "text": "Faith can chain or liberate — context decides.", "visual": "⛓️" }
      },
      "quiz": {
        "question": "How did Marx view religion's social role?",
        "options": ["As a force for equality", "As a tool that dulls pain and prevents rebellion", "As irrelevant to social life"],
        "correct": 1
      }
    },
    {
      "chapter_id": "anthropology--anthropology-of-religion--ch05-religion-and-society",
      "title": "Millenarian Movements",
      "is_free": false,
      "story": {
        "hook": { "text": "The Ghost Dance promised the return of dead ancestors and the end of white colonization. Belief became resistance.", "visual": "💃" },
        "buildup": { "text": "Millenarian movements predict a coming transformation — the end of the current order and birth of a perfect new world.", "visual": "🌅" },
        "discovery": { "text": "They arise among oppressed groups facing crisis: colonized peoples, the dispossessed, and communities in turmoil.", "visual": "⚡" },
        "twist": { "text": "These movements blend religion and politics. Spiritual renewal becomes a vehicle for resisting domination.", "visual": "✊" },
        "climax": { "text": "Millenarian movements reveal that religion isn't separate from politics. When hope dies, faith creates new visions.", "visual": "🌟" },
        "punchline": { "text": "When the present is unbearable, faith invents a future.", "visual": "🔮" }
      },
      "quiz": {
        "question": "When do millenarian movements typically arise?",
        "options": ["During times of prosperity", "Among oppressed groups facing crisis and domination", "Only in modern industrial societies"],
        "correct": 1
      }
    },
    {
      "chapter_id": "anthropology--anthropology-of-religion--ch05-religion-and-society",
      "title": "Religion and Healing",
      "is_free": false,
      "story": {
        "hook": { "text": "A healer lays hands on a patient and prays. The patient recovers. Placebo? Community support? Or something more?", "visual": "🙌" },
        "buildup": { "text": "In many cultures, healing is inseparable from religion. Illness has spiritual causes that require spiritual cures.", "visual": "🌿" },
        "discovery": { "text": "Ritual healing works through meaning. Believing in the cure, trusting the healer, and community support aid recovery.", "visual": "❤️" },
        "twist": { "text": "Biomedicine treats the body. Religious healing treats the person — their fears, their meaning, their relationships.", "visual": "🧠" },
        "climax": { "text": "Religious healing reveals that health isn't just biological. Meaning, belief, and social support are medicine too.", "visual": "💊" },
        "punchline": { "text": "Healing the spirit can heal the body.", "visual": "✨" }
      },
      "quiz": {
        "question": "How does religious healing work?",
        "options": ["It replaces all medical treatment", "Through meaning, belief, and community support", "It has no measurable effect ever"],
        "correct": 1
      }
    },
    {
      "chapter_id": "anthropology--anthropology-of-religion--ch05-religion-and-society",
      "title": "Civil Religion",
      "is_free": false,
      "story": {
        "hook": { "text": "Americans pledge allegiance, sing anthems, and honor sacred documents. The nation becomes the congregation.", "visual": "🇺🇸" },
        "buildup": { "text": "Robert Bellah coined civil religion — the quasi-religious rituals, symbols, and beliefs that sacralize the nation-state.", "visual": "🏛️" },
        "discovery": { "text": "National holidays, war memorials, and founding myths serve the same social function as traditional religious practices.", "visual": "🗽" },
        "twist": { "text": "Civil religion can unite diverse populations. But it can also sacralize nationalism, making dissent feel like blasphemy.", "visual": "🚩" },
        "climax": { "text": "Civil religion shows that the sacred isn't limited to churches. Nations create their own gods, saints, and commandments.", "visual": "📜" },
        "punchline": { "text": "Nations worship themselves through civil religion.", "visual": "🏛️" }
      },
      "quiz": {
        "question": "What is civil religion?",
        "options": ["Government-run churches", "Quasi-religious rituals and beliefs that sacralize the nation", "A type of atheism"],
        "correct": 1
      }
    },
    {
      "chapter_id": "anthropology--anthropology-of-religion--ch06-religion-in-modern-world",
      "title": "Secularization Debate",
      "is_free": true,
      "story": {
        "hook": { "text": "Europe's churches are empty. But globally, religion is booming. Is the world becoming more secular or not?", "visual": "⛪" },
        "buildup": { "text": "The secularization thesis predicted that modernity would cause religion to decline as science and reason advanced.", "visual": "📉" },
        "discovery": { "text": "In Europe, church attendance has dropped sharply. But in Africa, Asia, and Latin America, religion is growing fast.", "visual": "📈" },
        "twist": { "text": "The US breaks the pattern — highly modern yet deeply religious. Secularization is not a universal process after all.", "visual": "🇺🇸" },
        "climax": { "text": "Religion isn't dying. It's transforming. The secularization thesis described Europe, not the entire world.", "visual": "🌍" },
        "punchline": { "text": "Modernity changes religion; it doesn't end it.", "visual": "🔄" }
      },
      "quiz": {
        "question": "What does the secularization thesis predict?",
        "options": ["Religion will grow with modernity", "Modernity will cause religion to decline", "Religion and science are identical"],
        "correct": 1
      }
    },
    {
      "chapter_id": "anthropology--anthropology-of-religion--ch06-religion-in-modern-world",
      "title": "Fundamentalism",
      "is_free": false,
      "story": {
        "hook": { "text": "Return to the pure origins. Reject compromise. Fight modernity. Fundamentalism appears in every major religion.", "visual": "📕" },
        "buildup": { "text": "Fundamentalism is a reaction against modernity that demands strict return to what believers see as core scriptures.", "visual": "📜" },
        "discovery": { "text": "It emerged in Protestant Christianity, but parallel movements exist in Islam, Judaism, Hinduism, and Buddhism.", "visual": "🌐" },
        "twist": { "text": "Fundamentalism is itself modern. It uses technology, media, and political organizing — the very tools of modernity.", "visual": "📱" },
        "climax": { "text": "Fundamentalism isn't a return to the past. It's a modern reaction to modernity using modern tools to fight change.", "visual": "⚔️" },
        "punchline": { "text": "Rejecting modernity is itself a modern act.", "visual": "🔄" }
      },
      "quiz": {
        "question": "What is fundamentalism a reaction against?",
        "options": ["Ancient religious traditions", "Modernity and perceived moral decline", "All forms of organized religion"],
        "correct": 1
      }
    },
    {
      "chapter_id": "anthropology--anthropology-of-religion--ch06-religion-in-modern-world",
      "title": "New Religious Movements",
      "is_free": false,
      "story": {
        "hook": { "text": "Scientology, Rastafari, and the Baha'i Faith all emerged in the modern era. New religions keep appearing.", "visual": "🌟" },
        "buildup": { "text": "New religious movements are recently founded faiths that blend existing traditions with novel beliefs and practices.", "visual": "🔀" },
        "discovery": { "text": "They typically emerge around a charismatic leader who offers new revelation or reinterpretation of existing scriptures.", "visual": "📢" },
        "twist": { "text": "Calling them cults is a power move. Today's cult may become tomorrow's mainstream religion — Christianity once was one.", "visual": "⛪" },
        "climax": { "text": "New religious movements prove that religion is a living, evolving human creation, not a fixed set of ancient traditions.", "visual": "🌱" },
        "punchline": { "text": "Every old religion was once new.", "visual": "📖" }
      },
      "quiz": {
        "question": "What characterizes new religious movements?",
        "options": ["They never attract followers", "They blend existing traditions with novel beliefs around charismatic leaders", "They are always dangerous cults"],
        "correct": 1
      }
    },
    {
      "chapter_id": "anthropology--anthropology-of-religion--ch06-religion-in-modern-world",
      "title": "Religion and Globalization",
      "is_free": false,
      "story": {
        "hook": { "text": "Yoga studios in New York. Evangelical megachurches in Nigeria. Buddhism apps in London. Religion has gone global.", "visual": "🌐" },
        "buildup": { "text": "Globalization spreads religious ideas, practices, and movements across borders faster than ever before in history.", "visual": "✈️" },
        "discovery": { "text": "Pentecostalism is the fastest-growing religious movement — spreading from the US to Africa, Asia, and Latin America.", "visual": "📈" },
        "twist": { "text": "Global religions adapt locally. African Pentecostalism looks different from American — same faith, new local forms.", "visual": "🔄" },
        "climax": { "text": "Globalization doesn't create one world religion. It creates hybrid forms — local traditions reshaped by global flows.", "visual": "🌊" },
        "punchline": { "text": "Religion goes global; the local makes it its own.", "visual": "🌍" }
      },
      "quiz": {
        "question": "How does globalization affect religion?",
        "options": ["It creates one unified world religion", "It spreads religions that then adapt to local contexts", "It eliminates all religious practice"],
        "correct": 1
      }
    },
    {
      "chapter_id": "anthropology--anthropology-of-religion--ch06-religion-in-modern-world",
      "title": "Atheism and Nonbelief",
      "is_free": false,
      "story": {
        "hook": { "text": "Over a billion people claim no religion. But many still celebrate holidays, feel awe, and seek meaning. Is that secular?", "visual": "🤔" },
        "buildup": { "text": "Atheism rejects belief in gods. Nonbelief encompasses agnostics, nones, and the spiritually unaffiliated.", "visual": "📊" },
        "discovery": { "text": "Anthropologists study nonbelief as a cultural phenomenon — shaped by history, class, education, and national context.", "visual": "🔍" },
        "twist": { "text": "Even nonbelievers join in rituals: holidays, funerals, and life celebrations that carry quasi-religious functions.", "visual": "🎄" },
        "climax": { "text": "Atheism doesn't eliminate the human need for meaning, ritual, and community. It redirects them into secular forms.", "visual": "🔄" },
        "punchline": { "text": "Rejecting gods doesn't end the search for meaning.", "visual": "🔦" }
      },
      "quiz": {
        "question": "How do anthropologists study atheism?",
        "options": ["As a natural default state", "As a cultural phenomenon shaped by history and social context", "They don't study nonbelief at all"],
        "correct": 1
      }
    }
  ]
}
