{
  "id": "ecology--forest-ecosystems--t-temperate-rainforests",
  "version": 1,
  "subject": "Ecology",
  "subcategory": "Forest Ecosystems",
  "course_id": "ecology--forest-ecosystems",
  "chapter_id": "ecology--forest-ecosystems--ch03-temperate-forests",
  "title": "Temperate Rainforests",
  "emoji": "🌲",
  "color": "#15803D",
  "description": "A 60-second lesson on Temperate Rainforests.",
  "is_free": false,
  "published": true,
  "story": {
    "hook": {
      "text": "Rainforests exist outside the tropics too—cool, dripping, and draped in moss.",
      "visual": "🌧️"
    },
    "buildup": {
      "text": "The Pacific Northwest and southern Chile host temperate rainforests with over 3 meters of rain.",
      "visual": "💧"
    },
    "discovery": {
      "text": "Giant trees—Sitka spruce, western red cedar—tower 70 meters, rivaling tropical giants.",
      "visual": "🌲"
    },
    "twist": {
      "text": "These forests store more carbon per hectare than any other ecosystem on the planet.",
      "visual": "🌍"
    },
    "climax": {
      "text": "Logging has reduced temperate rainforests to scattered fragments along coastal mountains.",
      "visual": "🪓"
    },
    "punchline": {
      "text": "Not all rainforests are tropical. Some are cool.",
      "visual": "❄️"
    }
  },
  "quiz": {
    "question": "What makes temperate rainforests remarkable for carbon?",
    "options": [
      "They store more carbon per hectare than any other ecosystem",
      "They release the most CO₂",
      "They have no carbon cycle"
    ],
    "correct": 0
  }
}
