{
  "id": "human-resources--employee-engagement--t-transparent-communication",
  "version": 1,
  "subject": "Human Resources",
  "subcategory": "Employee Engagement",
  "course_id": "human-resources--employee-engagement",
  "chapter_id": "human-resources--employee-engagement--ch04-leadership-and-engagement",
  "title": "Transparent Communication",
  "emoji": "💪",
  "color": "#9333EA",
  "description": "Learn Transparent Communication in one minute.",
  "is_free": false,
  "published": true,
  "story": {
    "hook": {
      "text": "A company is restructuring. Leadership says nothing. Rumors fill the vacuum. Morale plummets before any change happens.",
      "visual": "🤫"
    },
    "buildup": {
      "text": "Transparent communication means sharing information honestly—good news and bad—rather than hiding behind corporate speak.",
      "visual": "📢"
    },
    "discovery": {
      "text": "Employees who feel informed are 4.6x more likely to feel empowered and engaged in their work.",
      "visual": "📊"
    },
    "twist": {
      "text": "Transparency isn't sharing everything—it's sharing what matters and explaining why certain things can't be shared yet.",
      "visual": "⚖️"
    },
    "climax": {
      "text": "Regular, honest updates—even when the news is uncertain—build trust. Silence breeds fear and speculation.",
      "visual": "🗣️"
    },
    "punchline": {
      "text": "In the absence of information, people assume the worst.",
      "visual": "💡"
    }
  },
  "quiz": {
    "question": "What happens when leadership is silent during uncertain times?",
    "options": [
      "Rumors fill the vacuum and morale drops",
      "Employees remain calm",
      "Productivity increases"
    ],
    "correct": 0
  }
}
