{
  "id": "cloud-computing--the-future-of-cloud--t-digital-twins-in-the-cloud",
  "version": 1,
  "subject": "Cloud Computing",
  "subcategory": "The Future of Cloud",
  "course_id": "cloud-computing--the-future-of-cloud",
  "chapter_id": "cloud-computing--the-future-of-cloud--ch05-emerging-technologies",
  "title": "Digital Twins in the Cloud",
  "emoji": "🔮",
  "color": "#A855F7",
  "description": "A 1-minute de-risking session on Digital Twins in the Cloud.",
  "is_free": false,
  "published": true,
  "story": {
    "hook": {
      "text": "BMW built a virtual copy of an entire factory in the cloud. They test changes digitally before touching the real thing.",
      "visual": "🏭"
    },
    "buildup": {
      "text": "A digital twin is a real-time virtual replica of a physical system, updated continuously with live sensor data.",
      "visual": "🔄"
    },
    "discovery": {
      "text": "AWS IoT TwinMaker, Azure Digital Twins, and NVIDIA Omniverse power digital twins of cities, factories, and more.",
      "visual": "🌆"
    },
    "twist": {
      "text": "Digital twins require massive compute and storage. Only the cloud can simulate entire physical systems in real time.",
      "visual": "💻"
    },
    "climax": {
      "text": "By 2027, half of large companies will use digital twins. Physical and digital worlds are merging through the cloud.",
      "visual": "🌐"
    },
    "punchline": {
      "text": "A virtual factory in the cloud. Test changes before reality.",
      "visual": "🧪"
    }
  },
  "quiz": {
    "question": "Why are digital twins only practical with cloud computing?",
    "options": [
      "They require massive compute and storage to simulate physical systems in real time",
      "Digital twins can only exist inside specific cloud provider ecosystems",
      "Physical systems cannot be monitored without cloud connectivity"
    ],
    "correct": 0
  }
}
