{
  "id": "art--color-theory--t-hue-saturation-and-value-explained",
  "version": 1,
  "subject": "Art & Design",
  "subcategory": "Color Theory",
  "course_id": "art--color-theory",
  "chapter_id": "art--color-theory--ch01-foundations-of-color",
  "title": "Hue, Saturation, and Value Explained",
  "emoji": "🎨",
  "color": "#E74C3C",
  "description": "A quick win: understand Hue, Saturation, and Value Explained.",
  "is_free": false,
  "published": true,
  "story": {
    "hook": {
      "text": "Two blues can feel completely different. Same hue, different saturation and value.",
      "visual": "🔵"
    },
    "buildup": {
      "text": "Hue is the color family: red, blue, green. Saturation is intensity: vivid vs. muted.",
      "visual": "📊"
    },
    "discovery": {
      "text": "Value is lightness or darkness. A navy blue and baby blue share a hue but differ in value.",
      "visual": "🌑"
    },
    "twist": {
      "text": "Value does the heavy lifting. A design with wrong hues but right values still reads clearly.",
      "visual": "📷"
    },
    "climax": {
      "text": "Test by converting to grayscale. If the contrast disappears, your values are off.",
      "visual": "⬛"
    },
    "punchline": {
      "text": "Hue gets the credit. Value does the work.",
      "visual": "💪"
    }
  },
  "quiz": {
    "question": "What is 'value' in color theory?",
    "options": [
      "The lightness or darkness of a color",
      "How expensive a pigment is",
      "The emotional meaning of a color"
    ],
    "correct": 0
  }
}
