{
  "id": "first-aid-safety--workplace-safety-science--t-the-hierarchy-of-controls",
  "version": 1,
  "subject": "First Aid & Safety",
  "subcategory": "Workplace Safety Science",
  "course_id": "first-aid-safety--workplace-safety-science",
  "chapter_id": "first-aid-safety--workplace-safety-science--ch03-hazard-recognition",
  "title": "The Hierarchy of Controls",
  "emoji": "🏗️",
  "color": "#B45309",
  "description": "Learn The Hierarchy of Controls in one minute.",
  "is_free": true,
  "published": true,
  "story": {
    "hook": {
      "text": "Telling workers to 'be more careful' is the weakest safety measure. Engineers know a better way.",
      "visual": "📐"
    },
    "buildup": {
      "text": "The hierarchy of controls ranks safety measures from most to least effective.",
      "visual": "📊"
    },
    "discovery": {
      "text": "Elimination is best. Then substitution, engineering controls, admin controls, and finally PPE.",
      "visual": "🔝"
    },
    "twist": {
      "text": "Most companies start at the bottom—giving workers hard hats instead of removing the falling hazard.",
      "visual": "⛑️"
    },
    "climax": {
      "text": "Working up the hierarchy costs more upfront but prevents more injuries per dollar spent.",
      "visual": "💰"
    },
    "punchline": {
      "text": "Remove the hazard. Don't just protect the worker standing next to it.",
      "visual": "🎯"
    }
  },
  "quiz": {
    "question": "What is the most effective level in the hierarchy of controls?",
    "options": [
      "Elimination of the hazard",
      "Personal protective equipment",
      "Administrative controls"
    ],
    "correct": 0
  }
}
