{
  "id": "biology--ecology-and-ecosystems--t-the-carbon-cycle",
  "version": 1,
  "subject": "Biology",
  "subcategory": "Ecology and Ecosystems",
  "course_id": "biology--ecology-and-ecosystems",
  "chapter_id": "biology--ecology-and-ecosystems--ch02-energy-and-nutrients",
  "title": "The Carbon Cycle",
  "emoji": "🌿",
  "color": "#059669",
  "description": "A short lesson to help you apply The Carbon Cycle.",
  "is_free": false,
  "published": true,
  "story": {
    "hook": {
      "text": "Carbon atoms cycle between air, water, rock, and living things in a loop that never stops.",
      "visual": "🔄"
    },
    "buildup": {
      "text": "Plants pull CO₂ from the air during photosynthesis and lock carbon into sugars.",
      "visual": "🌿"
    },
    "discovery": {
      "text": "Animals eat plants and release carbon back as CO₂ through respiration.",
      "visual": "🫁"
    },
    "twist": {
      "text": "Fossil fuels are ancient carbon locked underground. Burning them floods the atmosphere with CO₂.",
      "visual": "🏭"
    },
    "climax": {
      "text": "Excess atmospheric carbon drives global warming, disrupting ecosystems worldwide.",
      "visual": "🌡️"
    },
    "punchline": {
      "text": "Carbon cycles naturally. We sped it up.",
      "visual": "⏩"
    }
  },
  "quiz": {
    "question": "How do fossil fuels relate to the carbon cycle?",
    "options": [
      "Burning them releases ancient carbon into the atmosphere",
      "They absorb carbon from the air",
      "They have no effect on carbon levels"
    ],
    "correct": 0
  }
}
