{
  "id": "geology--minerals-and-rocks--t-regional-metamorphism",
  "version": 1,
  "subject": "Geology",
  "subcategory": "Minerals and Rocks",
  "course_id": "geology--minerals-and-rocks",
  "chapter_id": "geology--minerals-and-rocks--ch05-metamorphic-rocks",
  "title": "Regional Metamorphism",
  "emoji": "🪨",
  "color": "#92400E",
  "description": "A fast breakdown of Regional Metamorphism for builders.",
  "is_free": false,
  "published": true,
  "story": {
    "hook": {
      "text": "When continents collide, whole mountain ranges get squeezed and cooked. The change spans hundreds of kilometers.",
      "visual": "⛰️"
    },
    "buildup": {
      "text": "Regional metamorphism happens over large areas, driven by both intense pressure and heat from tectonic forces.",
      "visual": "🌍"
    },
    "discovery": {
      "text": "It produces foliated rocks like slate, schist, and gneiss, where minerals align in parallel layers or bands.",
      "visual": "📊"
    },
    "twist": {
      "text": "Metamorphic grade increases with depth: shale becomes slate, then phyllite, then schist, then gneiss.",
      "visual": "📈"
    },
    "climax": {
      "text": "Regional metamorphism is the signature of mountain building. Wherever you find schist, continents once collided.",
      "visual": "🏔️"
    },
    "punchline": {
      "text": "Colliding continents rewrite rock at depth.",
      "visual": "💥"
    }
  },
  "quiz": {
    "question": "What causes regional metamorphism?",
    "options": [
      "Contact with hot magma only",
      "Tectonic forces producing both heat and pressure over large areas",
      "Erosion at the surface"
    ],
    "correct": 1
  }
}
