{
  "id": "ecology--forest-ecosystems--t-the-wood-wide-web",
  "version": 1,
  "subject": "Ecology",
  "subcategory": "Forest Ecosystems",
  "course_id": "ecology--forest-ecosystems",
  "chapter_id": "ecology--forest-ecosystems--ch01-how-forests-work",
  "title": "The Wood Wide Web",
  "emoji": "🌲",
  "color": "#15803D",
  "description": "A 1-minute de-risking session on The Wood Wide Web.",
  "is_free": false,
  "published": true,
  "story": {
    "hook": {
      "text": "Trees in a forest share nutrients through underground fungal networks.",
      "visual": "🍄"
    },
    "buildup": {
      "text": "Mycorrhizal fungi connect roots of different trees, trading minerals for sugars.",
      "visual": "🔗"
    },
    "discovery": {
      "text": "Mother trees send carbon to shaded seedlings through these networks to help them grow.",
      "visual": "🌱"
    },
    "twist": {
      "text": "Some trees even warn neighbors of insect attacks through chemical signals in the web.",
      "visual": "⚠️"
    },
    "climax": {
      "text": "Clear-cutting destroys these networks, leaving replanted seedlings isolated and weaker.",
      "visual": "🪓"
    },
    "punchline": {
      "text": "Trees talk underground. We just started listening.",
      "visual": "👂"
    }
  },
  "quiz": {
    "question": "What do mycorrhizal fungi do for trees?",
    "options": [
      "Connect roots and trade minerals for sugars",
      "Decompose dead wood only",
      "Block water absorption"
    ],
    "correct": 0
  }
}
