{
  "id": "ai--history-of-ai--t-lessons-from-ai-s-failures",
  "version": 1,
  "subject": "AI & Agents",
  "subcategory": "The History of Artificial Intelligence",
  "course_id": "ai--history-of-ai",
  "chapter_id": "ai--history-of-ai--ch03-winters",
  "title": "Lessons from AI's Failures",
  "emoji": "📜",
  "color": "#7C3AED",
  "description": "Learn Lessons from AI's Failures in one minute.",
  "is_free": false,
  "published": true,
  "story": {
    "hook": {
      "text": "Every AI failure taught something crucial. The field grew stronger from its disasters.",
      "visual": "💪"
    },
    "buildup": {
      "text": "Perceptron limitations led to multi-layer networks. Expert system failures led to learning-based AI.",
      "visual": "🔄"
    },
    "discovery": {
      "text": "The key lesson: don't hard-code intelligence — let machines discover it from data.",
      "visual": "📊"
    },
    "twist": {
      "text": "The biggest failure was social, not technical — promising results before delivering them.",
      "visual": "📣"
    },
    "climax": {
      "text": "Today's researchers are more cautious with timelines, even if the media isn't.",
      "visual": "📰"
    },
    "punchline": {
      "text": "Failure is the best teacher — in AI and in life.",
      "visual": "🎓"
    }
  },
  "quiz": {
    "question": "What was the key lesson from AI's early failures?",
    "options": [
      "Let machines learn from data instead of hard-coding rules",
      "Abandon neural network research entirely",
      "Focus only on robotics"
    ],
    "correct": 0
  }
}
