{
  "id": "productivity--deep-work-and-focus--t-notification-culture",
  "version": 1,
  "subject": "Productivity",
  "subcategory": "Deep Work and Focus",
  "course_id": "productivity--deep-work-and-focus",
  "chapter_id": "productivity--deep-work-and-focus--ch01-the-attention-crisis",
  "title": "Notification Culture",
  "emoji": "🎯",
  "color": "#06B6D4",
  "description": "A micro-lesson that makes Notification Culture usable.",
  "is_free": false,
  "published": true,
  "story": {
    "hook": {
      "text": "The average smartphone user receives 80 notifications per day. Each one hijacks attention.",
      "visual": "🔔"
    },
    "buildup": {
      "text": "Notifications trigger a dopamine response. The brain treats each buzz as potentially important.",
      "visual": "🧪"
    },
    "discovery": {
      "text": "Research shows that even unread notifications reduce cognitive performance. Knowing they exist distracts.",
      "visual": "📵"
    },
    "twist": {
      "text": "Apps are designed by attention engineers. Their goal is your time, not your wellbeing.",
      "visual": "💻"
    },
    "climax": {
      "text": "Turning off non-essential notifications is one of the highest-leverage productivity changes.",
      "visual": "🔇"
    },
    "punchline": {
      "text": "Every notification is someone else's priority.",
      "visual": "🎯"
    }
  },
  "quiz": {
    "question": "What effect do even unread notifications have?",
    "options": [
      "They reduce cognitive performance",
      "They improve alertness",
      "They have no measurable effect"
    ],
    "correct": 0
  }
}
