{
  "id": "astronomy-and-space--the-history-of-astronomy--t-radio-astronomy-invisible-signals",
  "version": 1,
  "subject": "Astronomy & Space",
  "subcategory": "The History of Astronomy",
  "course_id": "astronomy-and-space--the-history-of-astronomy",
  "chapter_id": "astronomy-and-space--the-history-of-astronomy--ch04-modern-breakthroughs",
  "title": "Radio Astronomy: Invisible Signals",
  "emoji": "🔭",
  "color": "#10B981",
  "description": "A fast breakdown of Radio Astronomy: Invisible Signals for builders.",
  "is_free": false,
  "published": true,
  "story": {
    "hook": {
      "text": "Karl Jansky discovered radio waves from space in 1932 while investigating telephone static for Bell Labs.",
      "visual": "📡"
    },
    "buildup": {
      "text": "The signal peaked every 23 hours and 56 minutes—matching a sidereal day. It came from the center of the Milky Way.",
      "visual": "🌌"
    },
    "discovery": {
      "text": "Grote Reber built the first radio telescope in his backyard in 1937. For years, he was the only radio astronomer alive.",
      "visual": "🏠"
    },
    "twist": {
      "text": "Radio astronomy revealed pulsars, quasars, and the Cosmic Microwave Background—none visible through optical telescopes.",
      "visual": "🔭"
    },
    "climax": {
      "text": "Today, arrays like ALMA and the VLA map the invisible universe in stunning detail.",
      "visual": "📻"
    },
    "punchline": {
      "text": "Telephone static led to a new way of seeing the cosmos.",
      "visual": "👁️"
    }
  },
  "quiz": {
    "question": "How was radio astronomy accidentally discovered?",
    "options": [
      "Karl Jansky detected radio waves from space while investigating telephone static",
      "A military radar station picked up signals from Jupiter",
      "An amateur astronomer pointed a radio antenna at the Moon"
    ],
    "correct": 0
  }
}
