{
  "id": "accounting--financial-statements-decoded--t-goodwill-the-invisible-asset",
  "version": 1,
  "subject": "Accounting",
  "subcategory": "Financial Statements Decoded",
  "course_id": "accounting--financial-statements-decoded",
  "chapter_id": "accounting--financial-statements-decoded--ch01-the-balance-sheet",
  "title": "Goodwill: The Invisible Asset",
  "emoji": "📑",
  "color": "#166534",
  "description": "A fast breakdown of Goodwill: The Invisible Asset for builders.",
  "is_free": false,
  "published": true,
  "story": {
    "hook": {
      "text": "A company buys another for $10 billion, but the hard assets are only worth $6 billion. Where's the rest?",
      "visual": "🤔"
    },
    "buildup": {
      "text": "The $4 billion gap is goodwill—paying extra for brand reputation, customer loyalty, and talent.",
      "visual": "✨"
    },
    "discovery": {
      "text": "Goodwill sits on the balance sheet as an intangible asset after an acquisition.",
      "visual": "📋"
    },
    "twist": {
      "text": "If the acquisition flops, goodwill gets 'impaired'—written down, destroying reported equity.",
      "visual": "📉"
    },
    "climax": {
      "text": "Massive goodwill write-downs signal that a deal was overpriced. Markets punish it immediately.",
      "visual": "💸"
    },
    "punchline": {
      "text": "Goodwill is hope on a balance sheet.",
      "visual": "🌈"
    }
  },
  "quiz": {
    "question": "What does goodwill represent on a balance sheet?",
    "options": [
      "The premium paid above net asset value in an acquisition",
      "Cash in the bank",
      "Unpaid customer invoices"
    ],
    "correct": 0
  }
}
