{
  "id": "human-resources--recruitment-and-hiring--t-reference-checks-that-work",
  "version": 1,
  "subject": "Human Resources",
  "subcategory": "Recruitment and Hiring",
  "course_id": "human-resources--recruitment-and-hiring",
  "chapter_id": "human-resources--recruitment-and-hiring--ch04-selection-and-decision",
  "title": "Reference Checks That Work",
  "emoji": "🎯",
  "color": "#9333EA",
  "description": "A fast breakdown of Reference Checks That Work for builders.",
  "is_free": true,
  "published": true,
  "story": {
    "hook": {
      "text": "Most reference checks are useless. The candidate picks friendly referees who say nice things. That's not due diligence.",
      "visual": "📞"
    },
    "buildup": {
      "text": "Effective reference checks ask specific, behavioral questions—not just 'Would you hire them again?'",
      "visual": "📋"
    },
    "discovery": {
      "text": "The best question: 'What would I need to do to get the most out of this person?' It reveals strengths and gaps.",
      "visual": "💡"
    },
    "twist": {
      "text": "Back-channel references—people the candidate didn't list—often provide the most honest and useful feedback.",
      "visual": "🔍"
    },
    "climax": {
      "text": "A thorough reference check has saved companies from hiring charming interviewers who were terrible performers.",
      "visual": "🛡️"
    },
    "punchline": {
      "text": "Don't just check references. Actually learn from them.",
      "visual": "🎓"
    }
  },
  "quiz": {
    "question": "What makes a reference check more effective?",
    "options": [
      "Asking specific behavioral questions, not generic ones",
      "Only asking yes-or-no questions",
      "Skipping it entirely to save time"
    ],
    "correct": 0
  }
}
