{
  "id": "biology--evolutionary-biology--t-why-we-get-sick-evolutionary-medicine",
  "version": 1,
  "subject": "Biology",
  "subcategory": "Evolutionary Biology",
  "course_id": "biology--evolutionary-biology",
  "chapter_id": "biology--evolutionary-biology--ch06-evolution-and-medicine",
  "title": "Why We Get Sick: Evolutionary Medicine",
  "emoji": "🌳",
  "color": "#A855F7",
  "description": "Learn Why We Get Sick: Evolutionary Medicine in one minute.",
  "is_free": true,
  "published": true,
  "story": {
    "hook": {
      "text": "Our bodies evolved for a world of scarcity, movement, and infections. We now live in abundance and comfort.",
      "visual": "🍔"
    },
    "buildup": {
      "text": "Evolutionary medicine asks why natural selection left us vulnerable to diseases and disorders.",
      "visual": "🩺"
    },
    "discovery": {
      "text": "Our craving for sugar and fat was adaptive when food was scarce—now it drives obesity and diabetes.",
      "visual": "🍩"
    },
    "twist": {
      "text": "Lower back pain is common because our spine evolved for four-legged walking, not upright posture.",
      "visual": "🦴"
    },
    "climax": {
      "text": "Understanding evolutionary mismatches helps design better treatments and prevention strategies.",
      "visual": "💊"
    },
    "punchline": {
      "text": "Your body was built for a world that no longer exists.",
      "visual": "🌍"
    }
  },
  "quiz": {
    "question": "Why do humans crave sugar and fat?",
    "options": [
      "These cravings were adaptive when food was scarce",
      "Sugar is the brain's only fuel",
      "Modern food is designed to be addictive"
    ],
    "correct": 0
  }
}
