{
  "id": "devops--devops-security--t-sbom-software-bill-of-materials",
  "version": 1,
  "subject": "DevOps",
  "subcategory": "DevOps Security (DevSecOps)",
  "course_id": "devops--devops-security",
  "chapter_id": "devops--devops-security--ch03-supply-chain-security",
  "title": "SBOM: Software Bill of Materials",
  "emoji": "🔐",
  "color": "#059669",
  "description": "A 1-minute de-risking session on SBOM: Software Bill of Materials.",
  "is_free": false,
  "published": true,
  "story": {
    "hook": {
      "text": "Log4Shell hit. The CEO asked if they were affected. Nobody could answer — no one tracked dependencies.",
      "visual": "😰"
    },
    "buildup": {
      "text": "An SBOM lists every component: name, version, supplier, license, and relationships. A full inventory.",
      "visual": "📋"
    },
    "discovery": {
      "text": "SPDX and CycloneDX are standard SBOM formats. They're machine-readable so you can query them fast.",
      "visual": "🤖"
    },
    "twist": {
      "text": "SBOMs help your customers too. Sharing yours builds transparency and trust across the supply chain.",
      "visual": "🤝"
    },
    "climax": {
      "text": "Generate SBOMs in CI/CD. Every release gets a fresh, accurate bill of materials as an artifact.",
      "visual": "🏭"
    },
    "punchline": {
      "text": "Know what's in your software. An SBOM is the ingredient label.",
      "visual": "🏷️"
    }
  },
  "quiz": {
    "question": "What does an SBOM contain?",
    "options": [
      "A complete list of all software components, versions, and their relationships",
      "The source code of all dependencies",
      "Performance benchmarks for each library"
    ],
    "correct": 0
  }
}
